{
  "generator-jhipster": {
    "jhipsterVersion": "4.0.7",
    "baseName": "FPQuant",
    "packageName": "project",
    "packageFolder": "project",
    "serverPort": "8080",
    "authenticationType": "session",
    "hibernateCache": "no",
    "clusteredHttpSession": false,
    "websocket": false,
    "databaseType": "sql",
    "devDatabaseType": "h2Disk",
    "prodDatabaseType": "mysql",
    "searchEngine": false,
    "messageBroker": false,
    "serviceDiscoveryType": false,
    "buildTool": "maven",
    "enableSocialSignIn": false,
    "rememberMeKey": "4b0a277be99a0671e248655c5a914af55f2d8a2b",
    "clientFramework": "angular1",
    "useSass": false,
    "clientPackageManager": "yarn",
    "applicationType": "monolith",
    "testFrameworks": [],
    "jhiPrefix": "jhi",
    "enableTranslation": true,
    "nativeLanguage": "zh-cn",
    "languages": [
      "zh-cn",
      "en"
    ]
  }
}